Workbook

Sheet 1. Methods Reference
A1: Current Energy Saving Methods — Reference Guide & Expected Impact
A2: 7 Core Methods | How They Work | Expected Savings | NAAC Green Campus Evidence
A3: # | B3: Saving Method | C3: Description & How It Works | D3: Expected Saving | E3: Applicable Areas
A4: 1 | B4: Turning Off Equipment When Not in Use | C4: Awareness campaigns encourage staff and students to switch off lights, fans, projectors, and lab equipment when not needed. Reduces standby losses. Behavioural change — lowest cost, immediate impact. Signage, reminders, switch-off drills, designated monitors. | D4: 5–10% of total consumption | E4: All classrooms, labs, offices, corridors, hostels
A5: 2 | B5: Replacement of Incandescent/CFL with LED | C5: LEDs consume 75–80% less energy than traditional incandescent bulbs for same brightness. Longer lifespan (25,000–50,000 hrs vs 1,000 hrs incandescent). Reduced maintenance and e-waste. Quick payback (6–12 months). | D5: 75–80% lighting energy reduction | E5: All interior + exterior lighting, streetlights, hostels
A6: 3 | B6: Maintenance & Replacement of Old Appliances | C6: Routine servicing of ACs, fans, refrigerators, lab equipment. Old inefficient appliances phased out → replaced with 5-star BEE rated or inverter models. Reduces power wastage and failure rates. Preventive maintenance calendar. | D6: 15–25% per appliance category | E6: ACs, fans, refrigerators, water coolers, lab equipment
A7: 4 | B7: Power-Saving Mode in ICT Equipment | C7: All computers, printers, electronic equipment configured for energy-saving mode when idle. Monitors auto-sleep after 5–10 min. Screen brightness reduced. Hibernate mode after 30 min. | D7: 15–25% ICT energy reduction | E7: Computer labs, offices, admin, library
A8: 5 | B8: Master Switch Outside Each Room | C8: Single master switch outside classrooms and labs. Quick shutdown of ALL devices (lights, fans, projectors, ACs) when room vacated. Prevents human-error waste. Very low cost installation. | D8: 10–15% classroom consumption | E8: Classrooms, tutorial rooms, seminar halls, labs
A9: 6 | B9: Motion Sensors in Corridors & Toilets | C9: Automatic PIR motion sensor lighting in common areas — lights ON only when people present. Reduces load in corridors, washrooms, staircases where lights often left ON unnecessarily. | D9: 30–40% corridor/toilet lighting | E9: Corridors, staircases, washrooms, parking areas
A10: 7 | B10: Replacing Geysers with Solar Water Heating (SWHS) | C10: Traditional electric geysers are among least efficient devices. Solar water heating systems significantly cut electricity in hostels and residential buildings. Each SWHS saves 1,500–2,000 kWh/year. Reduces grid dependency. | D10: 60–70% hot water energy; 1,500–2,000 kWh/geyser/year | E10: Hostels, staff quarters, guest house, canteen

Sheet 2. Savings Tracker
A1: Energy Saving Methods — Before / After Tracker with Auto-Calculated Savings
A2: Yellow = Input (Before & After kWh) | Grey = Auto (Saving, %, Cost) | Tariff from Config
A3: Electricity Tariff (Rs/kWh) | E3: 8
A5: S.No. | B5: Saving Method | C5: Category (Behavioural / Technology / Maintenance / Renewable) | D5: Area / Location Applied | E5: Before (kWh/Month) | F5: After (kWh/Month) | G5: Saving (kWh/Month) [AUTO] | H5: Saving (%) [AUTO] | I5: Saving (Rs/Month) [AUTO] | J5: Saving (kWh/Year) [AUTO] | K5: Saving (Rs/Year) [AUTO] | L5: Status (Implemented / Partial / Planned) | M5: Evidence / Remarks
A6: 1 | B6: Turning off equipment when not in use | C6: Behavioural | D6: Campus-wide | E6: 5000 | F6: 4500 | G6: =IF(AND(E6>0,F6>=0),E6-F6,0) -> 500 | H6: =IF(E6>0,G6/E6*100,0) -> 10 | I6: =G6*$E$3 -> 4000 | J6: =G6*12 -> 6000 | K6: =I6*12 -> 48000
A7: 2 | B7: Replacement of incandescent/CFL with LED | C7: Technology | D7: All lighting | E7: 4000 | F7: 1000 | G7: =IF(AND(E7>0,F7>=0),E7-F7,0) -> 3000 | H7: =IF(E7>0,G7/E7*100,0) -> 75 | I7: =G7*$E$3 -> 24000 | J7: =G7*12 -> 36000 | K7: =I7*12 -> 288000
A8: 3 | B8: Maintenance & replacement of old appliances | C8: Maintenance | D8: ACs, fans, refrigerators, labs | E8: 6000 | F8: 4800 | G8: =IF(AND(E8>0,F8>=0),E8-F8,0) -> 1200 | H8: =IF(E8>0,G8/E8*100,0) -> 20 | I8: =G8*$E$3 -> 9600 | J8: =G8*12 -> 14400 | K8: =I8*12 -> 115200
A9: 4 | B9: Power-saving mode in ICT equipment | C9: Technology | D9: Computer labs, offices | E9: 3500 | F9: 2800 | G9: =IF(AND(E9>0,F9>=0),E9-F9,0) -> 700 | H9: =IF(E9>0,G9/E9*100,0) -> 20 | I9: =G9*$E$3 -> 5600 | J9: =G9*12 -> 8400 | K9: =I9*12 -> 67200
A10: 5 | B10: Master switch outside each room | C10: Technology | D10: Classrooms, seminar halls, labs | E10: 3000 | F10: 2550 | G10: =IF(AND(E10>0,F10>=0),E10-F10,0) -> 450 | H10: =IF(E10>0,G10/E10*100,0) -> 15 | I10: =G10*$E$3 -> 3600 | J10: =G10*12 -> 5400 | K10: =I10*12 -> 43200
A11: 6 | B11: Motion sensors in corridors & toilets | C11: Technology | D11: Corridors, washrooms, staircases | E11: 2500 | F11: 1500 | G11: =IF(AND(E11>0,F11>=0),E11-F11,0) -> 1000 | H11: =IF(E11>0,G11/E11*100,0) -> 40 | I11: =G11*$E$3 -> 8000 | J11: =G11*12 -> 12000 | K11: =I11*12 -> 96000
A12: 7 | B12: Replacing geysers with SWHS | C12: Renewable | D12: Hostels, staff quarters | E12: 4500 | F12: 1500 | G12: =IF(AND(E12>0,F12>=0),E12-F12,0) -> 3000 | H12: =IF(E12>0,G12/E12*100,0) -> 66.666667 | I12: =G12*$E$3 -> 24000 | J12: =G12*12 -> 36000 | K12: =I12*12 -> 288000
A13: 8 | G13: =IF(AND(E13>0,F13>=0),E13-F13,0) -> 0 | H13: =IF(E13>0,G13/E13*100,0) -> 0 | I13: =G13*$E$3 -> 0 | J13: =G13*12 -> 0 | K13: =I13*12 -> 0
A14: 9 | G14: =IF(AND(E14>0,F14>=0),E14-F14,0) -> 0 | H14: =IF(E14>0,G14/E14*100,0) -> 0 | I14: =G14*$E$3 -> 0 | J14: =G14*12 -> 0 | K14: =I14*12 -> 0
A15: 10 | G15: =IF(AND(E15>0,F15>=0),E15-F15,0) -> 0 | H15: =IF(E15>0,G15/E15*100,0) -> 0 | I15: =G15*$E$3 -> 0 | J15: =G15*12 -> 0 | K15: =I15*12 -> 0
A16: 11 | G16: =IF(AND(E16>0,F16>=0),E16-F16,0) -> 0 | H16: =IF(E16>0,G16/E16*100,0) -> 0 | I16: =G16*$E$3 -> 0 | J16: =G16*12 -> 0 | K16: =I16*12 -> 0
A17: 12 | G17: =IF(AND(E17>0,F17>=0),E17-F17,0) -> 0 | H17: =IF(E17>0,G17/E17*100,0) -> 0 | I17: =G17*$E$3 -> 0 | J17: =G17*12 -> 0 | K17: =I17*12 -> 0
A18: 13 | G18: =IF(AND(E18>0,F18>=0),E18-F18,0) -> 0 | H18: =IF(E18>0,G18/E18*100,0) -> 0 | I18: =G18*$E$3 -> 0 | J18: =G18*12 -> 0 | K18: =I18*12 -> 0
A19: 14 | G19: =IF(AND(E19>0,F19>=0),E19-F19,0) -> 0 | H19: =IF(E19>0,G19/E19*100,0) -> 0 | I19: =G19*$E$3 -> 0 | J19: =G19*12 -> 0 | K19: =I19*12 -> 0
A20: 15 | G20: =IF(AND(E20>0,F20>=0),E20-F20,0) -> 0 | H20: =IF(E20>0,G20/E20*100,0) -> 0 | I20: =G20*$E$3 -> 0 | J20: =G20*12 -> 0 | K20: =I20*12 -> 0
A21: 16 | G21: =IF(AND(E21>0,F21>=0),E21-F21,0) -> 0 | H21: =IF(E21>0,G21/E21*100,0) -> 0 | I21: =G21*$E$3 -> 0 | J21: =G21*12 -> 0 | K21: =I21*12 -> 0
A22: 17 | G22: =IF(AND(E22>0,F22>=0),E22-F22,0) -> 0 | H22: =IF(E22>0,G22/E22*100,0) -> 0 | I22: =G22*$E$3 -> 0 | J22: =G22*12 -> 0 | K22: =I22*12 -> 0
A23: 18 | G23: =IF(AND(E23>0,F23>=0),E23-F23,0) -> 0 | H23: =IF(E23>0,G23/E23*100,0) -> 0 | I23: =G23*$E$3 -> 0 | J23: =G23*12 -> 0 | K23: =I23*12 -> 0
A24: 19 | G24: =IF(AND(E24>0,F24>=0),E24-F24,0) -> 0 | H24: =IF(E24>0,G24/E24*100,0) -> 0 | I24: =G24*$E$3 -> 0 | J24: =G24*12 -> 0 | K24: =I24*12 -> 0
A25: 20 | G25: =IF(AND(E25>0,F25>=0),E25-F25,0) -> 0 | H25: =IF(E25>0,G25/E25*100,0) -> 0 | I25: =G25*$E$3 -> 0 | J25: =G25*12 -> 0 | K25: =I25*12 -> 0
A26: CAMPUS TOTAL ENERGY SAVINGS
A27: TOTALS | E27: =SUM(E6:E25) -> 28500 | F27: =SUM(F6:F25) -> 18650 | G27: =SUM(G6:G25) -> 9850 | H27: =IF(E27>0,G27/E27*100,0) -> 34.561404 | I27: =SUM(I6:I25) -> 78800 | J27: =SUM(J6:J25) -> 118200 | K27: =SUM(K6:K25) -> 945600
A29: Savings by Category
B30: Category | D30: Count | G30: kWh Saved/Mo | H30: Saving % | I30: Rs Saved/Mo | J30: kWh/Year | K30: Rs/Year | M30: % of Total Saving
A31: Behavioural | D31: =COUNTIF(C6:C25,"Behavioural") -> 1 | G31: =SUMPRODUCT((C6:C25="Behavioural")*G6:G25) -> 500 | I31: =SUMPRODUCT((C6:C25="Behavioural")*I6:I25) -> 4000 | J31: =G31*12 -> 6000 | K31: =I31*12 -> 48000 | M31: =IF(G27>0,G31/G27*100,0) -> 5.0761421
A32: Technology | D32: =COUNTIF(C6:C25,"Technology") -> 4 | G32: =SUMPRODUCT((C6:C25="Technology")*G6:G25) -> 5150 | I32: =SUMPRODUCT((C6:C25="Technology")*I6:I25) -> 41200 | J32: =G32*12 -> 61800 | K32: =I32*12 -> 494400 | M32: =IF(G27>0,G32/G27*100,0) -> 52.284264
A33: Maintenance | D33: =COUNTIF(C6:C25,"Maintenance") -> 1 | G33: =SUMPRODUCT((C6:C25="Maintenance")*G6:G25) -> 1200 | I33: =SUMPRODUCT((C6:C25="Maintenance")*I6:I25) -> 9600 | J33: =G33*12 -> 14400 | K33: =I33*12 -> 115200 | M33: =IF(G27>0,G33/G27*100,0) -> 12.182741
A34: Renewable | D34: =COUNTIF(C6:C25,"Renewable") -> 1 | G34: =SUMPRODUCT((C6:C25="Renewable")*G6:G25) -> 3000 | I34: =SUMPRODUCT((C6:C25="Renewable")*I6:I25) -> 24000 | J34: =G34*12 -> 36000 | K34: =I34*12 -> 288000 | M34: =IF(G27>0,G34/G27*100,0) -> 30.456853
A36: Implementation Status
A37: Implemented | E37: =COUNTIF(L6:L25,"Implemented") -> 0 | G37: =SUMPRODUCT((L6:L25="Implemented")*G6:G25) -> 0 | I37: =SUMPRODUCT((L6:L25="Implemented")*I6:I25) -> 0
A38: Partial | E38: =COUNTIF(L6:L25,"Partial") -> 0 | G38: =SUMPRODUCT((L6:L25="Partial")*G6:G25) -> 0 | I38: =SUMPRODUCT((L6:L25="Partial")*I6:I25) -> 0
A39: Planned | E39: =COUNTIF(L6:L25,"Planned") -> 0 | G39: =SUMPRODUCT((L6:L25="Planned")*G6:G25) -> 0 | I39: =SUMPRODUCT((L6:L25="Planned")*I6:I25) -> 0

Sheet 3. Location Detail
A1: Saving Method Impact by Location / Building — Granular Tracking
A2: Which method saves most in which building | Prioritizes future investment
A3: S.No. | B3: Building / Block | C3: Saving Method Applied | D3: Category | E3: Before (kWh/Mo) | F3: After (kWh/Mo) | G3: Saving (kWh/Mo) [AUTO] | H3: Saving (%) [AUTO] | I3: Saving (Rs/Mo) [AUTO] | J3: Remarks
A4: 1 | G4: =IF(AND(E4>0,F4>=0),E4-F4,0) -> 0 | H4: =IF(E4>0,G4/E4*100,0) -> 0 | I4: =G4*'2. Savings Tracker'!$E$3 -> 0
A5: 2 | G5: =IF(AND(E5>0,F5>=0),E5-F5,0) -> 0 | H5: =IF(E5>0,G5/E5*100,0) -> 0 | I5: =G5*'2. Savings Tracker'!$E$3 -> 0
A6: 3 | G6: =IF(AND(E6>0,F6>=0),E6-F6,0) -> 0 | H6: =IF(E6>0,G6/E6*100,0) -> 0 | I6: =G6*'2. Savings Tracker'!$E$3 -> 0
A7: 4 | G7: =IF(AND(E7>0,F7>=0),E7-F7,0) -> 0 | H7: =IF(E7>0,G7/E7*100,0) -> 0 | I7: =G7*'2. Savings Tracker'!$E$3 -> 0
A8: 5 | G8: =IF(AND(E8>0,F8>=0),E8-F8,0) -> 0 | H8: =IF(E8>0,G8/E8*100,0) -> 0 | I8: =G8*'2. Savings Tracker'!$E$3 -> 0
A9: 6 | G9: =IF(AND(E9>0,F9>=0),E9-F9,0) -> 0 | H9: =IF(E9>0,G9/E9*100,0) -> 0 | I9: =G9*'2. Savings Tracker'!$E$3 -> 0
A10: 7 | G10: =IF(AND(E10>0,F10>=0),E10-F10,0) -> 0 | H10: =IF(E10>0,G10/E10*100,0) -> 0 | I10: =G10*'2. Savings Tracker'!$E$3 -> 0
A11: 8 | G11: =IF(AND(E11>0,F11>=0),E11-F11,0) -> 0 | H11: =IF(E11>0,G11/E11*100,0) -> 0 | I11: =G11*'2. Savings Tracker'!$E$3 -> 0
A12: 9 | G12: =IF(AND(E12>0,F12>=0),E12-F12,0) -> 0 | H12: =IF(E12>0,G12/E12*100,0) -> 0 | I12: =G12*'2. Savings Tracker'!$E$3 -> 0
A13: 10 | G13: =IF(AND(E13>0,F13>=0),E13-F13,0) -> 0 | H13: =IF(E13>0,G13/E13*100,0) -> 0 | I13: =G13*'2. Savings Tracker'!$E$3 -> 0
A14: 11 | G14: =IF(AND(E14>0,F14>=0),E14-F14,0) -> 0 | H14: =IF(E14>0,G14/E14*100,0) -> 0 | I14: =G14*'2. Savings Tracker'!$E$3 -> 0
A15: 12 | G15: =IF(AND(E15>0,F15>=0),E15-F15,0) -> 0 | H15: =IF(E15>0,G15/E15*100,0) -> 0 | I15: =G15*'2. Savings Tracker'!$E$3 -> 0
... A53: 50 | G53: =IF(AND(E53>0,F53>=0),E53-F53,0) -> 0 | H53: =IF(E53>0,G53/E53*100,0) -> 0 | I53: =G53*'2. Savings Tracker'!$E$3 -> 0
A54: Location Totals
A55: TOTAL | E55: =SUM(E4:E53) -> 0 | F55: =SUM(F4:F53) -> 0 | G55: =SUM(G4:G53) -> 0 | H55: =IF(E55>0,G55/E55*100,0) -> 0 | I55: =SUM(I4:I53) -> 0

Sheet 4. YoY Trend
A1: Energy Saving Methods — 5-Year Trend
A2: Track cumulative savings growth for NAAC / Green Audit evidence
A3: S.No. | B3: Parameter | C3: Unit | D3: Year 1 | E3: Year 2 | F3: Year 3 | G3: Year 4 | H3: Year 5 | I3: 5-Year Change | J3: Growth (%) | K3: Trend
A4: 1 | B4: Methods Implemented (count) | I4: =IF(AND(D4>0,H4>0),H4-D4,0) -> 0 | J4: =IFERROR(IF(D4>0,(H4-D4)/D4*100,0),0) -> 0 | K4: =IF(I4>0,"Improving",IF(I4=0,"Stable","Declining")) -> Stable
A5: 2 | B5: Total Monthly Saving (kWh) | I5: =IF(AND(D5>0,H5>0),H5-D5,0) -> 0 | J5: =IFERROR(IF(D5>0,(H5-D5)/D5*100,0),0) -> 0 | K5: =IF(I5>0,"Improving",IF(I5=0,"Stable","Declining")) -> Stable
A6: 3 | B6: Total Monthly Cost Saving (Rs) | I6: =IF(AND(D6>0,H6>0),H6-D6,0) -> 0 | J6: =IFERROR(IF(D6>0,(H6-D6)/D6*100,0),0) -> 0 | K6: =IF(I6>0,"Improving",IF(I6=0,"Stable","Declining")) -> Stable
A7: 4 | B7: Annual kWh Saved | I7: =IF(AND(D7>0,H7>0),H7-D7,0) -> 0 | J7: =IFERROR(IF(D7>0,(H7-D7)/D7*100,0),0) -> 0 | K7: =IF(I7>0,"Improving",IF(I7=0,"Stable","Declining")) -> Stable
A8: 5 | B8: Annual Rs Saved | I8: =IF(AND(D8>0,H8>0),H8-D8,0) -> 0 | J8: =IFERROR(IF(D8>0,(H8-D8)/D8*100,0),0) -> 0 | K8: =IF(I8>0,"Improving",IF(I8=0,"Stable","Declining")) -> Stable
A9: 6 | B9: Overall Saving % | I9: =IF(AND(D9>0,H9>0),H9-D9,0) -> 0 | J9: =IFERROR(IF(D9>0,(H9-D9)/D9*100,0),0) -> 0 | K9: =IF(I9>0,"Improving",IF(I9=0,"Stable","Declining")) -> Stable
A10: 7 | B10: LED Transition % | I10: =IF(AND(D10>0,H10>0),H10-D10,0) -> 0 | J10: =IFERROR(IF(D10>0,(H10-D10)/D10*100,0),0) -> 0 | K10: =IF(I10>0,"Improving",IF(I10=0,"Stable","Declining")) -> Stable
A11: 8 | B11: Renewable Energy (kWh/mo) | I11: =IF(AND(D11>0,H11>0),H11-D11,0) -> 0 | J11: =IFERROR(IF(D11>0,(H11-D11)/D11*100,0),0) -> 0 | K11: =IF(I11>0,"Improving",IF(I11=0,"Stable","Declining")) -> Stable
A12: 9 | B12: Awareness Initiatives (count) | I12: =IF(AND(D12>0,H12>0),H12-D12,0) -> 0 | J12: =IFERROR(IF(D12>0,(H12-D12)/D12*100,0),0) -> 0 | K12: =IF(I12>0,"Improving",IF(I12=0,"Stable","Declining")) -> Stable
A13: 10 | B13: Carbon Offset (tonnes CO2/yr) | I13: =IF(AND(D13>0,H13>0),H13-D13,0) -> 0 | J13: =IFERROR(IF(D13>0,(H13-D13)/D13*100,0),0) -> 0 | K13: =IF(I13>0,"Improving",IF(I13=0,"Stable","Declining")) -> Stable

Sheet 5. Audit Checklist
A1: Energy Saving Methods — Audit & Evidence Checklist (NAAC / Green Audit)
A2: Evidence for each method + savings verification + future planning
A3: # | B3: Audit Item | C3: Requirement / Description | D3: Status (Y/X/IP) | E3: Date | F3: Reviewer
A4: 1 | B4: All 7 core methods documented | C4: Switch-off, LED, maintenance, power-save, master switch, motion sensors, SWHS
A5: 2 | B5: Before/after kWh recorded | C5: Baseline (before) and current (after) consumption per method documented
A6: 3 | B6: Savings auto-calculated correctly | C6: kWh saved = before - after; % = saved/before; Rs = kWh x tariff
A7: 4 | B7: Category classification | C7: Each method tagged: Behavioural, Technology, Maintenance, or Renewable
A8: 5 | B8: Location-wise detail available | C8: Building-level before/after data for each method applied
A9: 6 | B9: LED transition documented | C9: % of total fixtures converted to LED; count of LED vs non-LED
A10: 7 | B10: BEE star ratings documented | C10: Star rating of new appliances (ACs, refrigerators, fans) recorded
A11: 8 | B11: Power-save mode verified | C11: ICT equipment checked for sleep/hibernate/power-save configuration
A12: 9 | B12: Master switches installed | C12: Count and locations of master switches documented with photos
A13: 10 | B13: Motion sensors installed | C13: Count and locations of motion sensors; coverage area documented
A14: 11 | B14: SWHS capacity documented | C14: Solar water heater capacity (LPD), location, geysers replaced, kWh saved
A15: 12 | B15: Implementation status tracked | C15: Each method marked Implemented / Partial / Planned
... A23: 20 | B23: Reproducibility verified | C23: All savings reproducible from before/after data within ±5%
