Workbook

Sheet 1. Master Dashboard
A1: RECOMMENDATIONS FOR BETTER ENERGY EFFICIENCY — MASTER DASHBOARD
A2: All 16 Recommendations | Auto-Calculated Savings, ROI, Payback, CO₂ Reduction | A.Y. 2026–27
A4: Sl. | B4: Recommendation | C4: Category | D4: Est. Savings (kWh/yr) | E4: Est. Cost (₹) | F4: Tariff (₹/kWh) | G4: Annual Monetary Savings (₹) | H4: Payback Period (Years) | I4: 5-Year Net Savings (₹) | J4: 10-Year Net Savings (₹) | K4: CO₂ Reduction (tons/yr) | L4: Responsible Department
A5: 1 | B5: Replace old motors with energy-efficient motors | C5: Equipment Upgrade | D5: 20000 | E5: 500000 | F5: 8 | G5: =D5*F5 -> 160000 | H5: =IF(G5>0,E5/G5,0) -> 3.125 | I5: =G5*5-E5 -> 300000 | J5: =G5*10-E5 -> 1100000 | K5: =D5*0.82/1000 -> 16.4 | L5: Maintenance Dept.
A6: 2 | B6: Replace conventional chokes with electronic chokes | C6: Equipment Upgrade | D6: 5000 | E6: 100000 | F6: 8 | G6: =D6*F6 -> 40000 | H6: =IF(G6>0,E6/G6,0) -> 2.5 | I6: =G6*5-E6 -> 100000 | J6: =G6*10-E6 -> 300000 | K6: =D6*0.82/1000 -> 4.1 | L6: Electrical Dept.
A7: 3 | B7: Use motion sensors in corridors & toilets | C7: Automation & IoT | D7: 12000 | E7: 150000 | F7: 8 | G7: =D7*F7 -> 96000 | H7: =IF(G7>0,E7/G7,0) -> 1.5625 | I7: =G7*5-E7 -> 330000 | J7: =G7*10-E7 -> 810000 | K7: =D7*0.82/1000 -> 9.84 | L7: Energy Audit Committee
A8: 4 | B8: Replace all FTLs with LED lights | C8: Equipment Upgrade | D8: 36000 | E8: 400000 | F8: 8 | G8: =D8*F8 -> 288000 | H8: =IF(G8>0,E8/G8,0) -> 1.3888889 | I8: =G8*5-E8 -> 1040000 | J8: =G8*10-E8 -> 2480000 | K8: =D8*0.82/1000 -> 29.52 | L8: Electrical Dept.
A9: 5 | B9: Replace laser printers with inkjet printers | C9: Equipment Upgrade | D9: 4000 | E9: 80000 | F9: 8 | G9: =D9*F9 -> 32000 | H9: =IF(G9>0,E9/G9,0) -> 2.5 | I9: =G9*5-E9 -> 80000 | J9: =G9*10-E9 -> 240000 | K9: =D9*0.82/1000 -> 3.28 | L9: IT & Admin
A10: 6 | B10: Replace CRT monitors with LCD/LED monitors | C10: Equipment Upgrade | D10: 10000 | E10: 120000 | F10: 8 | G10: =D10*F10 -> 80000 | H10: =IF(G10>0,E10/G10,0) -> 1.5 | I10: =G10*5-E10 -> 280000 | J10: =G10*10-E10 -> 680000 | K10: =D10*0.82/1000 -> 8.2 | L10: IT & Admin
A11: 7 | B11: Replace old UPS with energy-efficient UPS | C11: Equipment Upgrade | D11: 8000 | E11: 250000 | F11: 8 | G11: =D11*F11 -> 64000 | H11: =IF(G11>0,E11/G11,0) -> 3.90625 | I11: =G11*5-E11 -> 70000 | J11: =G11*10-E11 -> 390000 | K11: =D11*0.82/1000 -> 6.56 | L11: IT/Infrastructure
A12: 8 | B12: Regular maintenance of batteries | C12: Maintenance | D12: 3000 | E12: 20000 | F12: 8 | G12: =D12*F12 -> 24000 | H12: =IF(G12>0,E12/G12,0) -> 0.83333333 | I12: =G12*5-E12 -> 100000 | J12: =G12*10-E12 -> 220000 | K12: =D12*0.82/1000 -> 2.46 | L12: Maintenance Dept.
A13: 9 | B13: Automate appliances with smart assistants | C13: Automation & IoT | D13: 2000 | E13: 50000 | F13: 8 | G13: =D13*F13 -> 16000 | H13: =IF(G13>0,E13/G13,0) -> 3.125 | I13: =G13*5-E13 -> 30000 | J13: =G13*10-E13 -> 110000 | K13: =D13*0.82/1000 -> 1.64 | L13: Energy Audit Committee
A14: 10 | B14: Increase natural lighting | C14: Building Design | D14: 1500 | E14: 30000 | F14: 8 | G14: =D14*F14 -> 12000 | H14: =IF(G14>0,E14/G14,0) -> 2.5 | I14: =G14*5-E14 -> 30000 | J14: =G14*10-E14 -> 90000 | K14: =D14*0.82/1000 -> 1.23 | L14: Infrastructure Office
A15: 11 | B15: Switch out incandescent lights | C15: Equipment Upgrade | D15: 6000 | E15: 50000 | F15: 8 | G15: =D15*F15 -> 48000 | H15: =IF(G15>0,E15/G15,0) -> 1.0416667 | I15: =G15*5-E15 -> 190000 | J15: =G15*10-E15 -> 430000 | K15: =D15*0.82/1000 -> 4.92 | L15: Electrical Dept.
A16: 12 | B16: Unplug battery chargers when not in use | C16: Behavioural | D16: 1000 | E16: 10000 | F16: 8 | G16: =D16*F16 -> 8000 | H16: =IF(G16>0,E16/G16,0) -> 1.25 | I16: =G16*5-E16 -> 30000 | J16: =G16*10-E16 -> 70000 | K16: =D16*0.82/1000 -> 0.82 | L16: All Staff & Students
... A20: 16 | B20: Install low-flow showerheads in hostels | C20: Building Design | D20: 4000 | E20: 25000 | F20: 8 | G20: =D20*F20 -> 32000 | H20: =IF(G20>0,E20/G20,0) -> 0.78125 | I20: =G20*5-E20 -> 135000 | J20: =G20*10-E20 -> 295000 | K20: =D20*0.82/1000 -> 3.28 | L20: Hostel Administration
B21: GRAND TOTAL | D21: =SUM(D5:D20) -> 127000 | E21: =SUM(E5:E20) -> 1925000 | G21: =SUM(G5:G20) -> 1016000 | H21: =IF(G21>0,E21/G21,0) -> 1.894685 | I21: =SUM(I5:I20) -> 3155000 | J21: =SUM(J5:J20) -> 8235000 | K21: =SUM(K5:K20) -> 104.14
B22: % of Total Savings | D22: =IF(D21>0,100,0) -> 100 | E22: =IF(E21>0,100,0) -> 100 | G22: =IF(G21>0,100,0) -> 100 | K22: =IF(K21>0,100,0) -> 100
A24: KEY INSTITUTIONAL METRICS — Auto-Calculated
A25: Total Annual Energy Savings (kWh) | G25: =D21 -> 127000
A26: Total Annual Monetary Savings (₹) | G26: =G21 -> 1016000
A27: Total Implementation Cost (₹) | G27: =E21 -> 1925000
A28: Overall Payback Period (Years) | G28: =H21 -> 1.894685
A29: 5-Year Net Institutional Savings (₹) | G29: =I21 -> 3155000
A30: 10-Year Net Institutional Savings (₹) | G30: =J21 -> 8235000
A31: Annual CO₂ Reduction (tons) | G31: =K21 -> 104.14
A32: Equivalent Trees Planted per Year | G32: =K21*1000/22 -> 4733.6364
A33: % Energy Reduction (if base = 500,000 kWh) | G33: =IF(500000>0,D21/500000*100,0) -> 25.4
A34: Highest-Impact Recommendation | G34: =INDEX(B5:B20,MATCH(MAX(D5:D20),D5:D20,0)) -> Replace all FTLs with LED lights
A35: Fastest Payback Recommendation | G35: =INDEX(B5:B20,MATCH(MIN(H5:H20),H5:H20,0)) -> Install low-flow showerheads in hostels

Sheet 2. Category Analysis
A1: CATEGORY-WISE ENERGY EFFICIENCY ANALYSIS
A2: Grouped by: Equipment Upgrade | Automation & IoT | Maintenance | Building Design | Behavioural
A4: # | B4: Category | C4: No. of Recommendations | D4: Total Savings (kWh/yr) | E4: Total Cost (₹) | F4: Total Annual Savings (₹) | G4: Avg Payback (Years) | H4: % of Total kWh Savings | I4: CO₂ Reduction (tons/yr)
A5: 1 | B5: Equipment Upgrade | C5: =COUNTIF('1. Master Dashboard'!C5:C20,B5) -> 8 | D5: =SUMIF('1. Master Dashboard'!C5:C20,B5,'1. Master Dashboard'!D5:D20) -> 91500 | E5: =SUMIF('1. Master Dashboard'!C5:C20,B5,'1. Master Dashboard'!E5:E20) -> 1530000 | F5: =SUMIF('1. Master Dashboard'!C5:C20,B5,'1. Master Dashboard'!G5:G20) -> 732000 | G5: =IF(F5>0,E5/F5,0) -> 2.0901639 | H5: =IF(D$10>0,D5/D$10*100,0) -> 72.047244 | I5: =D5*0.82/1000 -> 75.03
A6: 2 | B6: Automation & IoT | C6: =COUNTIF('1. Master Dashboard'!C5:C20,B6) -> 3 | D6: =SUMIF('1. Master Dashboard'!C5:C20,B6,'1. Master Dashboard'!D5:D20) -> 21000 | E6: =SUMIF('1. Master Dashboard'!C5:C20,B6,'1. Master Dashboard'!E5:E20) -> 270000 | F6: =SUMIF('1. Master Dashboard'!C5:C20,B6,'1. Master Dashboard'!G5:G20) -> 168000 | G6: =IF(F6>0,E6/F6,0) -> 1.6071429 | H6: =IF(D$10>0,D6/D$10*100,0) -> 16.535433 | I6: =D6*0.82/1000 -> 17.22
A7: 3 | B7: Maintenance | C7: =COUNTIF('1. Master Dashboard'!C5:C20,B7) -> 1 | D7: =SUMIF('1. Master Dashboard'!C5:C20,B7,'1. Master Dashboard'!D5:D20) -> 3000 | E7: =SUMIF('1. Master Dashboard'!C5:C20,B7,'1. Master Dashboard'!E5:E20) -> 20000 | F7: =SUMIF('1. Master Dashboard'!C5:C20,B7,'1. Master Dashboard'!G5:G20) -> 24000 | G7: =IF(F7>0,E7/F7,0) -> 0.83333333 | H7: =IF(D$10>0,D7/D$10*100,0) -> 2.3622047 | I7: =D7*0.82/1000 -> 2.46
A8: 4 | B8: Building Design | C8: =COUNTIF('1. Master Dashboard'!C5:C20,B8) -> 2 | D8: =SUMIF('1. Master Dashboard'!C5:C20,B8,'1. Master Dashboard'!D5:D20) -> 5500 | E8: =SUMIF('1. Master Dashboard'!C5:C20,B8,'1. Master Dashboard'!E5:E20) -> 55000 | F8: =SUMIF('1. Master Dashboard'!C5:C20,B8,'1. Master Dashboard'!G5:G20) -> 44000 | G8: =IF(F8>0,E8/F8,0) -> 1.25 | H8: =IF(D$10>0,D8/D$10*100,0) -> 4.3307087 | I8: =D8*0.82/1000 -> 4.51
A9: 5 | B9: Behavioural | C9: =COUNTIF('1. Master Dashboard'!C5:C20,B9) -> 2 | D9: =SUMIF('1. Master Dashboard'!C5:C20,B9,'1. Master Dashboard'!D5:D20) -> 6000 | E9: =SUMIF('1. Master Dashboard'!C5:C20,B9,'1. Master Dashboard'!E5:E20) -> 50000 | F9: =SUMIF('1. Master Dashboard'!C5:C20,B9,'1. Master Dashboard'!G5:G20) -> 48000 | G9: =IF(F9>0,E9/F9,0) -> 1.0416667 | H9: =IF(D$10>0,D9/D$10*100,0) -> 4.7244094 | I9: =D9*0.82/1000 -> 4.92
B10: TOTAL | C10: =SUM(C5:C9) -> 16 | D10: =SUM(D5:D9) -> 127000 | E10: =SUM(E5:E9) -> 1925000 | F10: =SUM(F5:F9) -> 1016000 | G10: =IF(F10>0,E10/F10,0) -> 1.894685 | H10: 100% | I10: =SUM(I5:I9) -> 104.14

Sheet 3. Department Tracker
A1: DEPARTMENT-WISE RESPONSIBILITY & IMPLEMENTATION TRACKER
A2: Auto-linked from Master Dashboard | Tracks each department's assigned savings target and cost responsibility
A4: # | B4: Responsible Department | C4: No. of Recommendations | D4: Total Savings (kWh/yr) | E4: Total Cost (₹) | F4: Annual Monetary Savings (₹) | G4: Avg Payback (Years) | H4: % of Total Savings
A5: 1 | B5: Maintenance Dept. | C5: =COUNTIF('1. Master Dashboard'!L5:L20,B5) -> 3 | D5: =SUMIF('1. Master Dashboard'!L5:L20,B5,'1. Master Dashboard'!D5:D20) -> 30000 | E5: =SUMIF('1. Master Dashboard'!L5:L20,B5,'1. Master Dashboard'!E5:E20) -> 590000 | F5: =SUMIF('1. Master Dashboard'!L5:L20,B5,'1. Master Dashboard'!G5:G20) -> 240000 | G5: =IF(F5>0,E5/F5,0) -> 2.4583333 | H5: =IF(D$15>0,D5/D$15*100,0) -> 23.622047
A6: 2 | B6: Electrical Dept. | C6: =COUNTIF('1. Master Dashboard'!L5:L20,B6) -> 3 | D6: =SUMIF('1. Master Dashboard'!L5:L20,B6,'1. Master Dashboard'!D5:D20) -> 47000 | E6: =SUMIF('1. Master Dashboard'!L5:L20,B6,'1. Master Dashboard'!E5:E20) -> 550000 | F6: =SUMIF('1. Master Dashboard'!L5:L20,B6,'1. Master Dashboard'!G5:G20) -> 376000 | G6: =IF(F6>0,E6/F6,0) -> 1.462766 | H6: =IF(D$15>0,D6/D$15*100,0) -> 37.007874
A7: 3 | B7: Energy Audit Committee | C7: =COUNTIF('1. Master Dashboard'!L5:L20,B7) -> 2 | D7: =SUMIF('1. Master Dashboard'!L5:L20,B7,'1. Master Dashboard'!D5:D20) -> 14000 | E7: =SUMIF('1. Master Dashboard'!L5:L20,B7,'1. Master Dashboard'!E5:E20) -> 200000 | F7: =SUMIF('1. Master Dashboard'!L5:L20,B7,'1. Master Dashboard'!G5:G20) -> 112000 | G7: =IF(F7>0,E7/F7,0) -> 1.7857143 | H7: =IF(D$15>0,D7/D$15*100,0) -> 11.023622
A8: 4 | B8: IT & Admin | C8: =COUNTIF('1. Master Dashboard'!L5:L20,B8) -> 2 | D8: =SUMIF('1. Master Dashboard'!L5:L20,B8,'1. Master Dashboard'!D5:D20) -> 14000 | E8: =SUMIF('1. Master Dashboard'!L5:L20,B8,'1. Master Dashboard'!E5:E20) -> 200000 | F8: =SUMIF('1. Master Dashboard'!L5:L20,B8,'1. Master Dashboard'!G5:G20) -> 112000 | G8: =IF(F8>0,E8/F8,0) -> 1.7857143 | H8: =IF(D$15>0,D8/D$15*100,0) -> 11.023622
A9: 5 | B9: IT/Infrastructure | C9: =COUNTIF('1. Master Dashboard'!L5:L20,B9) -> 1 | D9: =SUMIF('1. Master Dashboard'!L5:L20,B9,'1. Master Dashboard'!D5:D20) -> 8000 | E9: =SUMIF('1. Master Dashboard'!L5:L20,B9,'1. Master Dashboard'!E5:E20) -> 250000 | F9: =SUMIF('1. Master Dashboard'!L5:L20,B9,'1. Master Dashboard'!G5:G20) -> 64000 | G9: =IF(F9>0,E9/F9,0) -> 3.90625 | H9: =IF(D$15>0,D9/D$15*100,0) -> 6.2992126
A10: 6 | B10: Infrastructure Office | C10: =COUNTIF('1. Master Dashboard'!L5:L20,B10) -> 1 | D10: =SUMIF('1. Master Dashboard'!L5:L20,B10,'1. Master Dashboard'!D5:D20) -> 1500 | E10: =SUMIF('1. Master Dashboard'!L5:L20,B10,'1. Master Dashboard'!E5:E20) -> 30000 | F10: =SUMIF('1. Master Dashboard'!L5:L20,B10,'1. Master Dashboard'!G5:G20) -> 12000 | G10: =IF(F10>0,E10/F10,0) -> 2.5 | H10: =IF(D$15>0,D10/D$15*100,0) -> 1.1811024
A11: 7 | B11: All Staff & Students | C11: =COUNTIF('1. Master Dashboard'!L5:L20,B11) -> 1 | D11: =SUMIF('1. Master Dashboard'!L5:L20,B11,'1. Master Dashboard'!D5:D20) -> 1000 | E11: =SUMIF('1. Master Dashboard'!L5:L20,B11,'1. Master Dashboard'!E5:E20) -> 10000 | F11: =SUMIF('1. Master Dashboard'!L5:L20,B11,'1. Master Dashboard'!G5:G20) -> 8000 | G11: =IF(F11>0,E11/F11,0) -> 1.25 | H11: =IF(D$15>0,D11/D$15*100,0) -> 0.78740157
A12: 8 | B12: IT Dept. | C12: =COUNTIF('1. Master Dashboard'!L5:L20,B12) -> 1 | D12: =SUMIF('1. Master Dashboard'!L5:L20,B12,'1. Master Dashboard'!D5:D20) -> 5000 | E12: =SUMIF('1. Master Dashboard'!L5:L20,B12,'1. Master Dashboard'!E5:E20) -> 40000 | F12: =SUMIF('1. Master Dashboard'!L5:L20,B12,'1. Master Dashboard'!G5:G20) -> 40000 | G12: =IF(F12>0,E12/F12,0) -> 1 | H12: =IF(D$15>0,D12/D$15*100,0) -> 3.9370079
A13: 9 | B13: Hostel/Guest House | C13: =COUNTIF('1. Master Dashboard'!L5:L20,B13) -> 1 | D13: =SUMIF('1. Master Dashboard'!L5:L20,B13,'1. Master Dashboard'!D5:D20) -> 2500 | E13: =SUMIF('1. Master Dashboard'!L5:L20,B13,'1. Master Dashboard'!E5:E20) -> 30000 | F13: =SUMIF('1. Master Dashboard'!L5:L20,B13,'1. Master Dashboard'!G5:G20) -> 20000 | G13: =IF(F13>0,E13/F13,0) -> 1.5 | H13: =IF(D$15>0,D13/D$15*100,0) -> 1.9685039
A14: 10 | B14: Hostel Administration | C14: =COUNTIF('1. Master Dashboard'!L5:L20,B14) -> 1 | D14: =SUMIF('1. Master Dashboard'!L5:L20,B14,'1. Master Dashboard'!D5:D20) -> 4000 | E14: =SUMIF('1. Master Dashboard'!L5:L20,B14,'1. Master Dashboard'!E5:E20) -> 25000 | F14: =SUMIF('1. Master Dashboard'!L5:L20,B14,'1. Master Dashboard'!G5:G20) -> 32000 | G14: =IF(F14>0,E14/F14,0) -> 0.78125 | H14: =IF(D$15>0,D14/D$15*100,0) -> 3.1496063
B15: TOTAL | C15: =SUM(C5:C14) -> 16 | D15: =SUM(D5:D14) -> 127000 | E15: =SUM(E5:E14) -> 1925000 | F15: =SUM(F5:F14) -> 1016000 | G15: =IF(F15>0,E15/F15,0) -> 1.894685 | H15: 100%

Sheet 4. Implementation Plan
A1: PHASED IMPLEMENTATION PLAN & PROGRESS TRACKER
A2: Phase 1: Quick Wins (0–6 months) | Phase 2: Medium-Term (6–18 months) | Phase 3: Major Investments (18–36 months)
A4: # | B4: Recommendation | C4: Phase (1/2/3) | D4: Priority (H/M/L) | E4: Start Date | F4: Target Date | G4: Est. Cost (₹) | H4: Actual Cost (₹) | I4: % Complete | J4: Status | K4: Remarks
A5: 1 | B5: Replace old motors with energy-efficient motors | C5: 1 | D5: H | G5: 500000
A6: 2 | B6: Replace conventional chokes with electronic chokes | C6: 1 | D6: M | G6: 100000
A7: 3 | B7: Use motion sensors in corridors & toilets | C7: 2 | D7: H | G7: 150000
A8: 4 | B8: Replace all FTLs with LED lights | C8: 2 | D8: H | G8: 400000
A9: 5 | B9: Replace laser printers with inkjet printers | C9: 1 | D9: M | G9: 80000
A10: 6 | B10: Replace CRT monitors with LCD/LED monitors | C10: 1 | D10: M | G10: 120000
A11: 7 | B11: Replace old UPS with energy-efficient UPS | C11: 3 | D11: H | G11: 250000
A12: 8 | B12: Regular maintenance of batteries | C12: 1 | D12: H | G12: 20000
A13: 9 | B13: Automate appliances with smart assistants | C13: 2 | D13: M | G13: 50000
A14: 10 | B14: Increase natural lighting | C14: 3 | D14: L | G14: 30000
A15: 11 | B15: Switch out incandescent lights | C15: 1 | D15: H | G15: 50000
A16: 12 | B16: Unplug battery chargers when not in use | C16: 1 | D16: L | G16: 10000
... A20: 16 | B20: Install low-flow showerheads in hostels | C20: 2 | D20: M | G20: 25000
A22: Phase-wise Summary — Auto-Calculated
B23: Phase | C23: Count | G23: Est. Cost (₹) | H23: Actual Cost (₹) | I23: Avg % Complete
B24: Phase 1: Quick Wins (0–6 months) | C24: =COUNTIF(C5:C20,"1") -> 9 | G24: =SUMIF(C5:C20,"1",G5:G20) -> 950000 | H24: =SUMIF(C5:C20,"1",H5:H20) -> 0 | I24: =IFERROR(AVERAGEIF(C5:C20,"1",I5:I20),0) -> 0
B25: Phase 2: Medium-Term (6–18 months) | C25: =COUNTIF(C5:C20,"2") -> 5 | G25: =SUMIF(C5:C20,"2",G5:G20) -> 695000 | H25: =SUMIF(C5:C20,"2",H5:H20) -> 0 | I25: =IFERROR(AVERAGEIF(C5:C20,"2",I5:I20),0) -> 0
B26: Phase 3: Major Investments (18–36 months) | C26: =COUNTIF(C5:C20,"3") -> 2 | G26: =SUMIF(C5:C20,"3",G5:G20) -> 280000 | H26: =SUMIF(C5:C20,"3",H5:H20) -> 0 | I26: =IFERROR(AVERAGEIF(C5:C20,"3",I5:I20),0) -> 0

Sheet 5. Technical Details
A1: DETAILED TECHNICAL SPECIFICATIONS & JUSTIFICATION
A2: Technical rationale, before/after comparison, and quantified savings per recommendation
A3: # | B3: Recommendation | C3: Technical Description & Rationale | D3: Before (Old System) | E3: After (New/Upgraded) | F3: Quantified Improvement | G3: Standards / References
A4: 1 | B4: Replace old motors | C4: Old induction motors: 70–80% efficient, excess heat, high slip | D4: Standard: IE1 (70–80%) | E4: Upgrade: IE2/IE3 (90–95%) | F4: 10–15% power reduction per motor | G4: IS 12615, IEC 60034-30
A5: 2 | B5: Replace chokes | C5: Magnetic ballast: 10–15W loss/lamp, low power factor (0.5) | D5: Magnetic choke: 10–15W loss | E5: Electronic choke: <1W loss | F5: 15–20% energy saving, PF >0.9 | G5: IS 13021, IEC 61347
A6: 3 | B6: Motion sensors | C6: Corridors/toilets lit 24/7 unnecessarily; PIR sensors detect occupancy | D6: Constant ON: 100% duty | E6: Sensor: 60–70% duty | F6: 30–40% lighting savings | G6: IS 4648, ECBC 2017
A7: 4 | B7: FTL to LED | C7: FTL (36W+choke) = 46W vs LED tube (18W); better CRI, no flickering | D7: FTL: 46W per tube | E7: LED: 18W per tube | F7: 60–65% reduction per point | G7: IS 16102, IEC 62560
A8: 5 | B8: Laser to inkjet | C8: Laser fuser heats to 200°C (500–1000W); inkjet uses 30–50W | D8: Laser: 500–1000W peak | E8: Inkjet: 30–50W | F8: 80–90% energy reduction | G8: Energy Star, BEE Label
A9: 6 | B9: CRT to LCD/LED | C9: CRT ~100W, heavy, poor ergonomics; LCD/LED 25–40W, thin, crisp | D9: CRT: ~100W | E9: LCD/LED: 25–40W | F9: 60–75% reduction | G9: Energy Star, BIS
A10: 7 | B10: Old to efficient UPS | C10: Old UPS: 70–80% conversion; modern >95%; less heat waste | D10: Old UPS: 70–80% eff. | E10: New UPS: >95% eff. | F10: 15–25% standby savings | G10: IS 16242, IEC 62040
A11: 8 | B11: Battery maintenance | C11: Neglected batteries: sulfation, leakage, early failure, energy waste | D11: Unmaintained: 60–70% capacity | E11: Maintained: 90–95% capacity | F11: 20–30% efficiency gain | G11: IS 1651, IEEE 1188
A12: 9 | B12: Smart assistants | C12: Devices left ON by humans; IoT timers enforce schedules automatically | D12: Manual: human error prone | E12: Auto: scheduled ON/OFF | F12: Eliminates phantom loads | G12: IoT Standards, BIS
A13: 10 | B13: Natural lighting | C13: Dark corridors lit artificially; reflective surfaces redirect daylight | D13: No daylight harvesting | E13: Mirrors, light paint, skylights | F13: Reduces daytime lighting 30–50% | G13: NBC 2016, ECBC 2017, IGBC
A14: 11 | B14: Incandescent to LED | C14: Incandescent: 10% light / 90% heat; extreme inefficiency | D14: Incandescent: 60–100W | E14: LED: 7–12W | F14: 85–90% energy reduction | G14: IS 16102, BEE Star
A15: 12 | B15: Unplug chargers | C15: Idle chargers draw 0.5–2W each (vampire load); institutional scale adds up | D15: Plugged in: 0.5–2W idle | E15: Unplugged: 0W | F15: Eliminates vampire load | G15: Awareness campaign
... A19: 16 | B19: Low-flow showerheads | C19: Standard: 12–15 L/min; low-flow: 6–8 L/min; halves hot water demand | D19: Standard: 12–15 L/min | E19: Low-flow: 6–8 L/min | F19: 50% hot water energy savings | G19: IS 6392, WaterSense

Sheet 6. Before vs After
A1: BEFORE vs AFTER ENERGY COMPARISON — QUANTIFIED IMPACT
A2: Auto-calculated: Enter 'Before' consumption → formulas compute 'After', Savings, Cost Reduction & CO₂ impact
A4: # | B4: Recommendation | C4: Before (kWh/yr) | D4: After (kWh/yr) | E4: Savings (kWh/yr) | F4: % Reduction | G4: Annual Cost Savings (₹) | H4: CO₂ Saved (tons/yr)
A5: 1 | B5: Replace old motors with energy-efficient motors | C5: 160000 | D5: =C5-E5 -> 140000 | E5: ='1. Master Dashboard'!D5 -> 20000 | F5: =IF(C5>0,E5/C5*100,0) -> 12.5 | G5: =E5*8 -> 160000 | H5: =E5*0.82/1000 -> 16.4
A6: 2 | B6: Replace conventional chokes with electronic chokes | C6: 28571 | D6: =C6-E6 -> 23571 | E6: ='1. Master Dashboard'!D6 -> 5000 | F6: =IF(C6>0,E6/C6*100,0) -> 17.500263 | G6: =E6*8 -> 40000 | H6: =E6*0.82/1000 -> 4.1
A7: 3 | B7: Use motion sensors in corridors & toilets | C7: 34286 | D7: =C7-E7 -> 22286 | E7: ='1. Master Dashboard'!D7 -> 12000 | F7: =IF(C7>0,E7/C7*100,0) -> 34.999708 | G7: =E7*8 -> 96000 | H7: =E7*0.82/1000 -> 9.84
A8: 4 | B8: Replace all FTLs with LED lights | C8: 55385 | D8: =C8-E8 -> 19385 | E8: ='1. Master Dashboard'!D8 -> 36000 | F8: =IF(C8>0,E8/C8*100,0) -> 64.999549 | G8: =E8*8 -> 288000 | H8: =E8*0.82/1000 -> 29.52
A9: 5 | B9: Replace laser printers with inkjet printers | C9: 4706 | D9: =C9-E9 -> 706 | E9: ='1. Master Dashboard'!D9 -> 4000 | F9: =IF(C9>0,E9/C9*100,0) -> 84.997875 | G9: =E9*8 -> 32000 | H9: =E9*0.82/1000 -> 3.28
A10: 6 | B10: Replace CRT monitors with LCD/LED monitors | C10: 15385 | D10: =C10-E10 -> 5385 | E10: ='1. Master Dashboard'!D10 -> 10000 | F10: =IF(C10>0,E10/C10*100,0) -> 64.998375 | G10: =E10*8 -> 80000 | H10: =E10*0.82/1000 -> 8.2
A11: 7 | B11: Replace old UPS with energy-efficient UPS | C11: 40000 | D11: =C11-E11 -> 32000 | E11: ='1. Master Dashboard'!D11 -> 8000 | F11: =IF(C11>0,E11/C11*100,0) -> 20 | G11: =E11*8 -> 64000 | H11: =E11*0.82/1000 -> 6.56
A12: 8 | B12: Regular maintenance of batteries | C12: 12000 | D12: =C12-E12 -> 9000 | E12: ='1. Master Dashboard'!D12 -> 3000 | F12: =IF(C12>0,E12/C12*100,0) -> 25 | G12: =E12*8 -> 24000 | H12: =E12*0.82/1000 -> 2.46
A13: 9 | B13: Automate appliances with smart assistants | C13: 13333 | D13: =C13-E13 -> 11333 | E13: ='1. Master Dashboard'!D13 -> 2000 | F13: =IF(C13>0,E13/C13*100,0) -> 15.000375 | G13: =E13*8 -> 16000 | H13: =E13*0.82/1000 -> 1.64
A14: 10 | B14: Increase natural lighting | C14: 3750 | D14: =C14-E14 -> 2250 | E14: ='1. Master Dashboard'!D14 -> 1500 | F14: =IF(C14>0,E14/C14*100,0) -> 40 | G14: =E14*8 -> 12000 | H14: =E14*0.82/1000 -> 1.23
A15: 11 | B15: Switch out incandescent lights | C15: 6818 | D15: =C15-E15 -> 818 | E15: ='1. Master Dashboard'!D15 -> 6000 | F15: =IF(C15>0,E15/C15*100,0) -> 88.002347 | G15: =E15*8 -> 48000 | H15: =E15*0.82/1000 -> 4.92
A16: 12 | B16: Unplug battery chargers when not in use | C16: 10000 | D16: =C16-E16 -> 9000 | E16: ='1. Master Dashboard'!D16 -> 1000 | F16: =IF(C16>0,E16/C16*100,0) -> 10 | G16: =E16*8 -> 8000 | H16: =E16*0.82/1000 -> 0.82
... A20: 16 | B20: Install low-flow showerheads in hostels | C20: 8000 | D20: =C20-E20 -> 4000 | E20: ='1. Master Dashboard'!D20 -> 4000 | F20: =IF(C20>0,E20/C20*100,0) -> 50 | G20: =E20*8 -> 32000 | H20: =E20*0.82/1000 -> 3.28
B21: TOTAL | C21: =SUM(C5:C20) -> 470734 | D21: =SUM(D5:D20) -> 343734 | E21: =SUM(E5:E20) -> 127000 | F21: =IF(C21>0,E21/C21*100,0) -> 26.979143 | G21: =SUM(G5:G20) -> 1016000 | H21: =SUM(H5:H20) -> 104.14

Sheet 7. Carbon Impact
A1: ENVIRONMENTAL & CARBON IMPACT — ALL 16 RECOMMENDATIONS
A2: Auto-linked: CO₂, SO₂, NOx reduction + lifetime projections | Indian grid: 0.82 tCO₂/MWh
A4: # | B4: Recommendation | C4: Savings (kWh/yr) | D4: CO₂ Avoided (tons/yr) | E4: SO₂ Avoided (kg/yr) | F4: NOx Avoided (kg/yr) | G4: Trees Equivalent/yr
A5: 1 | B5: ='1. Master Dashboard'!B5 -> Replace old motors with energy-efficient motors | C5: ='1. Master Dashboard'!D5 -> 20000 | D5: =C5*0.82/1000 -> 16.4 | E5: =C5*0.005 -> 100 | F5: =C5*0.003 -> 60 | G5: =IF(D5>0,D5*1000/22,0) -> 745.45455
A6: 2 | B6: ='1. Master Dashboard'!B6 -> Replace conventional chokes with electronic chokes | C6: ='1. Master Dashboard'!D6 -> 5000 | D6: =C6*0.82/1000 -> 4.1 | E6: =C6*0.005 -> 25 | F6: =C6*0.003 -> 15 | G6: =IF(D6>0,D6*1000/22,0) -> 186.36364
A7: 3 | B7: ='1. Master Dashboard'!B7 -> Use motion sensors in corridors & toilets | C7: ='1. Master Dashboard'!D7 -> 12000 | D7: =C7*0.82/1000 -> 9.84 | E7: =C7*0.005 -> 60 | F7: =C7*0.003 -> 36 | G7: =IF(D7>0,D7*1000/22,0) -> 447.27273
A8: 4 | B8: ='1. Master Dashboard'!B8 -> Replace all FTLs with LED lights | C8: ='1. Master Dashboard'!D8 -> 36000 | D8: =C8*0.82/1000 -> 29.52 | E8: =C8*0.005 -> 180 | F8: =C8*0.003 -> 108 | G8: =IF(D8>0,D8*1000/22,0) -> 1341.8182
A9: 5 | B9: ='1. Master Dashboard'!B9 -> Replace laser printers with inkjet printers | C9: ='1. Master Dashboard'!D9 -> 4000 | D9: =C9*0.82/1000 -> 3.28 | E9: =C9*0.005 -> 20 | F9: =C9*0.003 -> 12 | G9: =IF(D9>0,D9*1000/22,0) -> 149.09091
A10: 6 | B10: ='1. Master Dashboard'!B10 -> Replace CRT monitors with LCD/LED monitors | C10: ='1. Master Dashboard'!D10 -> 10000 | D10: =C10*0.82/1000 -> 8.2 | E10: =C10*0.005 -> 50 | F10: =C10*0.003 -> 30 | G10: =IF(D10>0,D10*1000/22,0) -> 372.72727
A11: 7 | B11: ='1. Master Dashboard'!B11 -> Replace old UPS with energy-efficient UPS | C11: ='1. Master Dashboard'!D11 -> 8000 | D11: =C11*0.82/1000 -> 6.56 | E11: =C11*0.005 -> 40 | F11: =C11*0.003 -> 24 | G11: =IF(D11>0,D11*1000/22,0) -> 298.18182
A12: 8 | B12: ='1. Master Dashboard'!B12 -> Regular maintenance of batteries | C12: ='1. Master Dashboard'!D12 -> 3000 | D12: =C12*0.82/1000 -> 2.46 | E12: =C12*0.005 -> 15 | F12: =C12*0.003 -> 9 | G12: =IF(D12>0,D12*1000/22,0) -> 111.81818
A13: 9 | B13: ='1. Master Dashboard'!B13 -> Automate appliances with smart assistants | C13: ='1. Master Dashboard'!D13 -> 2000 | D13: =C13*0.82/1000 -> 1.64 | E13: =C13*0.005 -> 10 | F13: =C13*0.003 -> 6 | G13: =IF(D13>0,D13*1000/22,0) -> 74.545455
A14: 10 | B14: ='1. Master Dashboard'!B14 -> Increase natural lighting | C14: ='1. Master Dashboard'!D14 -> 1500 | D14: =C14*0.82/1000 -> 1.23 | E14: =C14*0.005 -> 7.5 | F14: =C14*0.003 -> 4.5 | G14: =IF(D14>0,D14*1000/22,0) -> 55.909091
A15: 11 | B15: ='1. Master Dashboard'!B15 -> Switch out incandescent lights | C15: ='1. Master Dashboard'!D15 -> 6000 | D15: =C15*0.82/1000 -> 4.92 | E15: =C15*0.005 -> 30 | F15: =C15*0.003 -> 18 | G15: =IF(D15>0,D15*1000/22,0) -> 223.63636
A16: 12 | B16: ='1. Master Dashboard'!B16 -> Unplug battery chargers when not in use | C16: ='1. Master Dashboard'!D16 -> 1000 | D16: =C16*0.82/1000 -> 0.82 | E16: =C16*0.005 -> 5 | F16: =C16*0.003 -> 3 | G16: =IF(D16>0,D16*1000/22,0) -> 37.272727
... A20: 16 | B20: ='1. Master Dashboard'!B20 -> Install low-flow showerheads in hostels | C20: ='1. Master Dashboard'!D20 -> 4000 | D20: =C20*0.82/1000 -> 3.28 | E20: =C20*0.005 -> 20 | F20: =C20*0.003 -> 12 | G20: =IF(D20>0,D20*1000/22,0) -> 149.09091
B21: ANNUAL TOTAL | C21: =SUM(C5:C20) -> 127000 | D21: =SUM(D5:D20) -> 104.14 | E21: =SUM(E5:E20) -> 635 | F21: =SUM(F5:F20) -> 381 | G21: =SUM(G5:G20) -> 4733.6364
B22: 10-YEAR LIFETIME | C22: =C21*10 -> 1270000 | D22: =D21*10 -> 1041.4 | E22: =E21*10 -> 6350 | F22: =F21*10 -> 3810 | G22: =G21*10 -> 47336.364
B23: 25-YEAR LIFETIME | C23: =C21*25 -> 3175000 | D23: =D21*25 -> 2603.5 | E23: =E21*25 -> 15875 | F23: =F21*25 -> 9525 | G23: =G21*25 -> 118340.91

Sheet 8. Data Quality Audit
A1: ENERGY EFFICIENCY RECOMMENDATIONS — DATA QUALITY & AUDIT CHECKLIST
A2: 20-point verification for data accuracy, financial integrity & implementation readiness
A3: # | B3: Quality Check | C3: Description | D3: Status (✓/✗/IP) | E3: Date | F3: Reviewer
A4: 1 | B4: Baseline energy consumption | C4: Institutional baseline verified from utility bills for 12 consecutive months (kWh)
A5: 2 | B5: Appliance inventory accuracy | C5: Appliance counts verified against physical inspection or departmental inventory registers
A6: 3 | B6: Wattage ratings verified | C6: Rated wattage for each appliance type cross-checked against nameplate or BEE database
A7: 4 | B7: Savings estimates methodology | C7: kWh savings calculated using accepted engineering formulas, not estimates or vendor claims
A8: 5 | B8: Cost estimates sourced | C8: Implementation costs verified against minimum 3 vendor quotations or GeM portal rates
A9: 6 | B9: Tariff rate current | C9: Electricity tariff matches latest DISCOM tariff order for institutional HT/LT category
A10: 7 | B10: Payback calculation | C10: Payback = Cost ÷ Annual Savings; verified manually for all 16 recommendations
A11: 8 | B11: CO₂ emission factor | C11: CEA CO₂ Baseline Database (0.82 tCO₂/MWh) or latest published figure used consistently
A12: 9 | B12: Category classification | C12: Each recommendation correctly classified (Equipment/Automation/Maintenance/Building/Behavioural)
A13: 10 | B13: Department assignment | C13: Responsible departments confirmed by institutional authority; no overlaps or gaps
A14: 11 | B14: Phase assignment rationale | C14: Phase 1/2/3 assignment based on cost, complexity, and institutional readiness assessment
A15: 12 | B15: Priority assignment | C15: H/M/L priorities verified against energy audit report recommendations
... A23: 20 | B23: Annual review mechanism | C23: Annual review and reporting mechanism established for tracking actual vs. projected savings
A25: Checks Passed | D25: =COUNTIF(D4:D23,"✓") -> 0
A26: Completion Rate (%) | D26: =IFERROR(COUNTIF(D4:D23,"✓")/20*100,0) -> 0
