Workbook

Sheet 1. Waste Categories
A1: WASTE CATEGORIES, DISPOSAL METHODS & REGULATORY FRAMEWORK
A2: Complete waste classification for HEIs | Aligned with SWM Rules 2016, BMW Rules 2016, E-Waste Rules 2022
A4: # | B4: Waste Type | C4: Sub-Category | D4: Disposal Method | E4: Regulatory Framework | F4: Campus Relevance
A5: 1 | B5: E-Waste | C5: Monitors, desktops, laptops, printers, UPS | D5: Collected in separate bins → Authorized e-waste recycler | E5: E-Waste (Management) Rules, 2022 | F5: Computer labs, IT dept, offices
A6: 2 | B6: Bio-Degradable – Organic | C6: Food waste, garden waste, leaves, flowers | D6: Composting / Vermicomposting → Organic manure for campus gardens | E6: SWM Rules, 2016 | F6: Canteen, hostels, gardens
A7: 3 | B7: Bio-Degradable – Inorganic | C7: Chemicals, glass, lab reagents | D7: Disposed in lined earthen pits; neutralization before disposal | E7: BMW Rules, 2016 / HW Rules, 2016 | F7: Chemistry & science labs
A8: 4 | B8: Domestic Waste | C8: Food leftovers from hostels & canteens | D8: Cattle feeding / biogas plant feed | E8: SWM Rules, 2016 | F8: Hostels, mess, canteen
A9: 5 | B9: Electrical Waste | C9: Tube lights, bulbs, wires, stoves, fans | D9: Collected in separate bins → Safe recycling / disposal | E9: E-Waste Rules, 2022 / HW Rules | F9: All buildings campus-wide
A10: 6 | B10: Paper Waste | C10: Newspapers, answer sheets, office paper | D10: Sold for recycling to authorized recyclers | E10: SWM Rules, 2016 | F10: Offices, exam cells, library
A11: 7 | B11: Metal Scrap | C11: Steel furniture frames, lab equipment, pipes | D11: Sold for recycling; income per net weight | E11: SWM Rules, 2016 | F11: Workshop, labs, stores
A12: 8 | B12: Timber Waste | C12: Furniture scraps, wooden pallets, doors | D12: Stored → Repaired/reused OR sold as scrap | E12: SWM Rules, 2016 | F12: Carpentry, hostels, offices
A13: 9 | B13: Resins, Fuel, Oil, Grease | C13: Lab chemicals, DG set oil, workshop grease | D13: Disposed in lined earthen pits with caution | E13: HW Rules, 2016 | F13: Workshop, DG room, labs
A14: 10 | B14: Sanitary Waste | C14: Used sanitary products | D14: Incineration facility at ladies' hostels | E14: BMW Rules, 2016 | F14: Ladies' hostels
A15: 11 | B15: Plastic Waste | C15: Bottles, packaging, lab plastics | D15: Collected in dustbins → Municipal / recycler pickup | E15: Plastic Waste Management Rules, 2016 | F15: Campus-wide
A16: 12 | B16: Scrap Equipment | C16: Non-functional lab equipment, furniture | D16: Stored in designated storeroom → Bulk auction/sale | E16: GFR / State surplus rules | F16: Labs, workshops, stores
... A18: 14 | B18: Biomedical Waste | C18: First aid waste, dispensary sharps | D18: Collected in colour-coded bins → Authorized CBWTF | E18: BMW Rules, 2016 | F18: Health centre / dispensary

Sheet 2. Monthly Waste Data
A1: MONTHLY WASTE GENERATION DATA — A.Y. 2026–27
A2: Enter waste quantity (kg) per category per month | All totals & percentages auto-calculated
A3: Campus Population (students + staff) → | E3: 5000
A5: Sl. | B5: Month | C5: Organic (kg) | D5: Paper (kg) | E5: Plastic (kg) | F5: E-Waste (kg) | G5: Metal Scrap (kg) | H5: Electrical (kg) | I5: Glass / Chemical (kg) | J5: Timber (kg) | K5: Sanitary (kg) | L5: Construction (kg) | M5: Domestic Food (kg) | N5: Biomedical (kg) | O5: Oil/Grease (kg) | P5: Other (kg) | Q5: TOTAL (kg) | R5: Per Capita (kg/person/month)
A6: 1 | B6: April 2026 | Q6: =SUM(C6:P6) -> 0 | R6: =IF($E$3>0,Q6/$E$3,0) -> 0
A7: 2 | B7: May 2026 | Q7: =SUM(C7:P7) -> 0 | R7: =IF($E$3>0,Q7/$E$3,0) -> 0
A8: 3 | B8: June 2026 | Q8: =SUM(C8:P8) -> 0 | R8: =IF($E$3>0,Q8/$E$3,0) -> 0
A9: 4 | B9: July 2026 | Q9: =SUM(C9:P9) -> 0 | R9: =IF($E$3>0,Q9/$E$3,0) -> 0
A10: 5 | B10: August 2026 | Q10: =SUM(C10:P10) -> 0 | R10: =IF($E$3>0,Q10/$E$3,0) -> 0
A11: 6 | B11: September 2026 | Q11: =SUM(C11:P11) -> 0 | R11: =IF($E$3>0,Q11/$E$3,0) -> 0
A12: 7 | B12: October 2026 | Q12: =SUM(C12:P12) -> 0 | R12: =IF($E$3>0,Q12/$E$3,0) -> 0
A13: 8 | B13: November 2026 | Q13: =SUM(C13:P13) -> 0 | R13: =IF($E$3>0,Q13/$E$3,0) -> 0
A14: 9 | B14: December 2026 | Q14: =SUM(C14:P14) -> 0 | R14: =IF($E$3>0,Q14/$E$3,0) -> 0
A15: 10 | B15: January 2027 | Q15: =SUM(C15:P15) -> 0 | R15: =IF($E$3>0,Q15/$E$3,0) -> 0
A16: 11 | B16: February 2027 | Q16: =SUM(C16:P16) -> 0 | R16: =IF($E$3>0,Q16/$E$3,0) -> 0
A17: 12 | B17: March 2027 | Q17: =SUM(C17:P17) -> 0 | R17: =IF($E$3>0,Q17/$E$3,0) -> 0
B18: ANNUAL TOTAL | C18: =SUM(C6:C17) -> 0 | D18: =SUM(D6:D17) -> 0 | E18: =SUM(E6:E17) -> 0 | F18: =SUM(F6:F17) -> 0 | G18: =SUM(G6:G17) -> 0 | H18: =SUM(H6:H17) -> 0 | I18: =SUM(I6:I17) -> 0 | J18: =SUM(J6:J17) -> 0 | ... Q18: =SUM(Q6:Q17) -> 0 | R18: =IF($E$3>0,Q18/$E$3,0) -> 0
B19: MONTHLY AVERAGE | C19: =IFERROR(AVERAGE(C6:C17),0) -> 0 | D19: =IFERROR(AVERAGE(D6:D17),0) -> 0 | E19: =IFERROR(AVERAGE(E6:E17),0) -> 0 | F19: =IFERROR(AVERAGE(F6:F17),0) -> 0 | G19: =IFERROR(AVERAGE(G6:G17),0) -> 0 | H19: =IFERROR(AVERAGE(H6:H17),0) -> 0 | I19: =IFERROR(AVERAGE(I6:I17),0) -> 0 | J19: =IFERROR(AVERAGE(J6:J17),0) -> 0 | ... R19: =IFERROR(AVERAGE(R6:R17),0) -> 0
B20: % DISTRIBUTION | C20: =IF(Q18>0,C18/Q18*100,0) -> 0 | D20: =IF(Q18>0,D18/Q18*100,0) -> 0 | E20: =IF(Q18>0,E18/Q18*100,0) -> 0 | F20: =IF(Q18>0,F18/Q18*100,0) -> 0 | G20: =IF(Q18>0,G18/Q18*100,0) -> 0 | H20: =IF(Q18>0,H18/Q18*100,0) -> 0 | I20: =IF(Q18>0,I18/Q18*100,0) -> 0 | J20: =IF(Q18>0,J18/Q18*100,0) -> 0 | K20: =IF(Q18>0,K18/Q18*100,0) -> 0 | L20: =IF(Q18>0,L18/Q18*100,0) -> 0 | M20: =IF(Q18>0,M18/Q18*100,0) -> 0 | N20: =IF(Q18>0,N18/Q18*100,0) -> 0 | O20: =IF(Q18>0,O18/Q18*100,0) -> 0 | P20: =IF(Q18>0,P18/Q18*100,0) -> 0

Sheet 3. Segregation & Disposal
A1: WASTE SEGREGATION, RECYCLING & DISPOSAL TRACKER — A.Y. 2026–27
A2: Tracks fate of each waste category: Recycled / Composted / Incinerated / Landfilled / Sold | Auto-calculated diversion rate
A4: Sl. | B4: Waste Category | C4: Total Generated (kg/year) | D4: Recycled (kg) | E4: Composted (kg) | F4: Incinerated (kg) | G4: Sold / Reused (kg) | H4: Landfilled (kg) | I4: Diversion Rate (%) | J4: Disposal Method
A5: 1 | B5: Organic / Food Waste | C5: ='2. Monthly Waste Data'!C18 -> 0 | I5: =IF(C5>0,(D5+E5+G5)/C5*100,0) -> 0 | J5: Composting / Vermicomposting
A6: 2 | B6: Paper Waste | C6: ='2. Monthly Waste Data'!D18 -> 0 | I6: =IF(C6>0,(D6+E6+G6)/C6*100,0) -> 0 | J6: Sold to authorized recycler
A7: 3 | B7: Plastic Waste | C7: ='2. Monthly Waste Data'!E18 -> 0 | I7: =IF(C7>0,(D7+E7+G7)/C7*100,0) -> 0 | J7: Municipal / recycler pickup
A8: 4 | B8: E-Waste | C8: ='2. Monthly Waste Data'!F18 -> 0 | I8: =IF(C8>0,(D8+E8+G8)/C8*100,0) -> 0 | J8: Authorized e-waste recycler
A9: 5 | B9: Metal Scrap | C9: ='2. Monthly Waste Data'!G18 -> 0 | I9: =IF(C9>0,(D9+E9+G9)/C9*100,0) -> 0 | J9: Sold per net weight
A10: 6 | B10: Electrical Waste | C10: ='2. Monthly Waste Data'!H18 -> 0 | I10: =IF(C10>0,(D10+E10+G10)/C10*100,0) -> 0 | J10: Safe recycling bins
A11: 7 | B11: Glass / Chemical | C11: ='2. Monthly Waste Data'!I18 -> 0 | I11: =IF(C11>0,(D11+E11+G11)/C11*100,0) -> 0 | J11: Lined earthen pits
A12: 8 | B12: Timber Waste | C12: ='2. Monthly Waste Data'!J18 -> 0 | I12: =IF(C12>0,(D12+E12+G12)/C12*100,0) -> 0 | J12: Stored / repaired / sold
A13: 9 | B13: Sanitary Waste | C13: ='2. Monthly Waste Data'!K18 -> 0 | I13: =IF(C13>0,(D13+E13+G13)/C13*100,0) -> 0 | J13: Incineration facility
A14: 10 | B14: Construction Waste | C14: ='2. Monthly Waste Data'!L18 -> 0 | I14: =IF(C14>0,(D14+E14+G14)/C14*100,0) -> 0 | J14: Campus landfilling / reuse
A15: 11 | B15: Domestic Food Waste | C15: ='2. Monthly Waste Data'!M18 -> 0 | I15: =IF(C15>0,(D15+E15+G15)/C15*100,0) -> 0 | J15: Cattle feeding / biogas
A16: 12 | B16: Biomedical Waste | C16: ='2. Monthly Waste Data'!N18 -> 0 | I16: =IF(C16>0,(D16+E16+G16)/C16*100,0) -> 0 | J16: Authorized CBWTF
A17: 13 | B17: Oil / Grease | C17: ='2. Monthly Waste Data'!O18 -> 0 | I17: =IF(C17>0,(D17+E17+G17)/C17*100,0) -> 0 | J17: Lined earthen pits
A18: 14 | B18: Other | C18: ='2. Monthly Waste Data'!P18 -> 0 | I18: =IF(C18>0,(D18+E18+G18)/C18*100,0) -> 0 | J18: Various
B19: GRAND TOTAL | C19: =SUM(C5:C18) -> 0 | D19: =SUM(D5:D18) -> 0 | E19: =SUM(E5:E18) -> 0 | F19: =SUM(F5:F18) -> 0 | G19: =SUM(G5:G18) -> 0 | H19: =SUM(H5:H18) -> 0 | I19: =IF(C19>0,(D19+E19+G19)/C19*100,0) -> 0
A21: Waste Management KPIs — Auto-Calculated
A22: Total Waste Generated (kg/year) | F22: =C19 -> 0
A23: Total Waste Recycled (kg) | F23: =D19 -> 0
A24: Total Waste Composted (kg) | F24: =E19 -> 0
A25: Total Waste Sold / Reused (kg) | F25: =G19 -> 0
A26: Total Waste Landfilled (kg) | F26: =H19 -> 0
A27: Total Waste Incinerated (kg) | F27: =F19 -> 0
A28: Overall Landfill Diversion Rate (%) | F28: =I19 -> 0
A29: Landfill Dependency (%) | F29: =IF(C19>0,H19/C19*100,0) -> 0
A30: Waste per Capita (kg/person/year) | F30: =IF('2. Monthly Waste Data'!E3>0,C19/'2. Monthly Waste Data'!E3,0) -> 0
A31: Revenue from Recycling (₹ — enter below) | F31: =0 -> 0

Sheet 4. Source-wise Inventory
A1: SOURCE-WISE WASTE GENERATION INVENTORY — A.Y. 2026–27
A2: Waste generated per campus source: Hostels, Canteen, Labs, Offices, Construction | Identifies top generators
A4: Sl. | B4: Campus Source | C4: Bio-Degradable (kg/month) | D4: Paper (kg/month) | E4: Plastic (kg/month) | F4: E-Waste (kg/month) | G4: Hazardous (kg/month) | H4: Other (kg/month) | I4: Total (kg/month) | J4: % of Campus Total
A5: 1 | B5: Hostel – A | I5: =SUM(C5:H5) -> 0 | J5: =IF(I$25>0,I5/I$25*100,0) -> 0
A6: 2 | B6: Hostel – B | I6: =SUM(C6:H6) -> 0 | J6: =IF(I$25>0,I6/I$25*100,0) -> 0
A7: 3 | B7: Hostel – C | I7: =SUM(C7:H7) -> 0 | J7: =IF(I$25>0,I7/I$25*100,0) -> 0
A8: 4 | B8: Hostel – D | I8: =SUM(C8:H8) -> 0 | J8: =IF(I$25>0,I8/I$25*100,0) -> 0
A9: 5 | B9: Canteen / Mess | I9: =SUM(C9:H9) -> 0 | J9: =IF(I$25>0,I9/I$25*100,0) -> 0
A10: 6 | B10: Academic Block – A | I10: =SUM(C10:H10) -> 0 | J10: =IF(I$25>0,I10/I$25*100,0) -> 0
A11: 7 | B11: Academic Block – B | I11: =SUM(C11:H11) -> 0 | J11: =IF(I$25>0,I11/I$25*100,0) -> 0
A12: 8 | B12: Science / Engineering Labs | I12: =SUM(C12:H12) -> 0 | J12: =IF(I$25>0,I12/I$25*100,0) -> 0
A13: 9 | B13: Library | I13: =SUM(C13:H13) -> 0 | J13: =IF(I$25>0,I13/I$25*100,0) -> 0
A14: 10 | B14: Administrative Block | I14: =SUM(C14:H14) -> 0 | J14: =IF(I$25>0,I14/I$25*100,0) -> 0
A15: 11 | B15: Examination Cell | I15: =SUM(C15:H15) -> 0 | J15: =IF(I$25>0,I15/I$25*100,0) -> 0
A16: 12 | B16: Workshop Complex | I16: =SUM(C16:H16) -> 0 | J16: =IF(I$25>0,I16/I$25*100,0) -> 0
... A24: 20 | B24: Other | I24: =SUM(C24:H24) -> 0 | J24: =IF(I$25>0,I24/I$25*100,0) -> 0
B25: CAMPUS TOTAL (Monthly) | C25: =SUM(C5:C24) -> 0 | D25: =SUM(D5:D24) -> 0 | E25: =SUM(E5:E24) -> 0 | F25: =SUM(F5:F24) -> 0 | G25: =SUM(G5:G24) -> 0 | H25: =SUM(H5:H24) -> 0 | I25: =SUM(I5:I24) -> 0
B26: ANNUAL ESTIMATE (×12) | C26: =C25*12 -> 0 | D26: =D25*12 -> 0 | E26: =E25*12 -> 0 | F26: =F25*12 -> 0 | G26: =G25*12 -> 0 | H26: =H25*12 -> 0 | I26: =I25*12 -> 0
A28: Top Waste Generator — Auto-Identified
A29: Highest Waste Generator | F29: =IFERROR(INDEX(B5:B24,MATCH(MAX(I5:I24),I5:I24,0)),"N/A") -> Hostel – A

Sheet 5. Composting & Organic
A1: COMPOSTING & ORGANIC WASTE PROCESSING LOG — A.Y. 2026–27
A2: Tracks vermicomposting / pit composting input → output | Calculates compost conversion rate & cost savings
A3: Fertilizer cost saved per kg compost (₹) → | E3: 5
A5: Sl. | B5: Month | C5: Organic Waste Collected (kg) | D5: Food Waste from Canteen (kg) | E5: Garden Waste (kg) | F5: Total Input (kg) | G5: Compost Output (kg) | H5: Conversion Rate (%) | I5: Compost Used in Gardens (kg) | J5: Fertilizer Cost Saved (₹)
A6: 1 | B6: April 2026 | F6: =SUM(C6:E6) -> 0 | H6: =IF(F6>0,G6/F6*100,0) -> 0 | J6: =I6*$E$3 -> 0
A7: 2 | B7: May 2026 | F7: =SUM(C7:E7) -> 0 | H7: =IF(F7>0,G7/F7*100,0) -> 0 | J7: =I7*$E$3 -> 0
A8: 3 | B8: June 2026 | F8: =SUM(C8:E8) -> 0 | H8: =IF(F8>0,G8/F8*100,0) -> 0 | J8: =I8*$E$3 -> 0
A9: 4 | B9: July 2026 | F9: =SUM(C9:E9) -> 0 | H9: =IF(F9>0,G9/F9*100,0) -> 0 | J9: =I9*$E$3 -> 0
A10: 5 | B10: August 2026 | F10: =SUM(C10:E10) -> 0 | H10: =IF(F10>0,G10/F10*100,0) -> 0 | J10: =I10*$E$3 -> 0
A11: 6 | B11: September 2026 | F11: =SUM(C11:E11) -> 0 | H11: =IF(F11>0,G11/F11*100,0) -> 0 | J11: =I11*$E$3 -> 0
A12: 7 | B12: October 2026 | F12: =SUM(C12:E12) -> 0 | H12: =IF(F12>0,G12/F12*100,0) -> 0 | J12: =I12*$E$3 -> 0
A13: 8 | B13: November 2026 | F13: =SUM(C13:E13) -> 0 | H13: =IF(F13>0,G13/F13*100,0) -> 0 | J13: =I13*$E$3 -> 0
A14: 9 | B14: December 2026 | F14: =SUM(C14:E14) -> 0 | H14: =IF(F14>0,G14/F14*100,0) -> 0 | J14: =I14*$E$3 -> 0
A15: 10 | B15: January 2027 | F15: =SUM(C15:E15) -> 0 | H15: =IF(F15>0,G15/F15*100,0) -> 0 | J15: =I15*$E$3 -> 0
A16: 11 | B16: February 2027 | F16: =SUM(C16:E16) -> 0 | H16: =IF(F16>0,G16/F16*100,0) -> 0 | J16: =I16*$E$3 -> 0
A17: 12 | B17: March 2027 | F17: =SUM(C17:E17) -> 0 | H17: =IF(F17>0,G17/F17*100,0) -> 0 | J17: =I17*$E$3 -> 0
B18: ANNUAL TOTAL | C18: =SUM(C6:C17) -> 0 | D18: =SUM(D6:D17) -> 0 | E18: =SUM(E6:E17) -> 0 | F18: =SUM(F6:F17) -> 0 | G18: =SUM(G6:G17) -> 0 | H18: =IF(F18>0,G18/F18*100,0) -> 0 | I18: =SUM(I6:I17) -> 0 | J18: =SUM(J6:J17) -> 0

Sheet 6. Recycling Revenue
A1: REVENUE FROM RECYCLING, SCRAP SALE & WASTE MONETIZATION — A.Y. 2026–27
A2: Tracks income from sale of paper, metal, plastic, e-waste, timber, scrap equipment | Auto-totalled
A4: Sl. | B4: Recyclable Item | C4: Quantity Sold (kg / units) | D4: Rate per kg (₹) | E4: Revenue Generated (₹) | F4: Buyer / Recycler | G4: Date of Sale | H4: Receipt / Invoice No.
A5: 1 | B5: Paper / Newspaper | E5: =C5*D5 -> 0
A6: 2 | B6: Metal Scrap (Steel) | E6: =C6*D6 -> 0
A7: 3 | B7: Plastic (bottles, packaging) | E7: =C7*D7 -> 0
A8: 4 | B8: E-Waste (monitors, printers) | E8: =C8*D8 -> 0
A9: 5 | B9: Electrical Waste (bulbs, wires) | E9: =C9*D9 -> 0
A10: 6 | B10: Timber / Furniture Scrap | E10: =C10*D10 -> 0
A11: 7 | B11: Scrap Equipment (lab/office) | E11: =C11*D11 -> 0
A12: 8 | B12: Compost / Organic Manure Sold | E12: =C12*D12 -> 0
A13: 9 | B13: Construction Debris (reusable) | E13: =C13*D13 -> 0
A14: 10 | B14: Other Recyclables | E14: =C14*D14 -> 0
A15: 11 | E15: =C15*D15 -> 0
A16: 12 | E16: =C16*D16 -> 0
A17: 13 | E17: =C17*D17 -> 0
A18: 14 | E18: =C18*D18 -> 0
A19: 15 | E19: =C19*D19 -> 0
A20: 16 | E20: =C20*D20 -> 0
A21: 17 | E21: =C21*D21 -> 0
A22: 18 | E22: =C22*D22 -> 0
A23: 19 | E23: =C23*D23 -> 0
A24: 20 | E24: =C24*D24 -> 0
B25: TOTAL ANNUAL REVENUE | E25: =SUM(E5:E24) -> 0

Sheet 7. Roadmap & Policy
A1: WASTE MANAGEMENT ROADMAP & POLICY–ACTION–OUTCOME TRACKER
A2: Short (0–1yr) / Mid (1–3yr) / Long (3–5yr) goals | 6 Policy objectives from HEI framework
A3: # | B3: Initiative / Policy | C3: Description & Action Steps | D3: Timeline (Short/Mid/Long) | E3: Status (Done/IP/Planned) | F3: Est. Budget (₹ Lakhs) | G3: Evidence
A4: 1 | B4: Baseline waste audit | C4: First campus-wide audit: identify waste types, quantities, sources across hostels, canteen, labs, offices | D4: Short | E4: IP
A5: 2 | B5: Color-coded segregation bins | C5: Introduce green (wet), blue (dry), red (hazardous) bins at all high-traffic locations | D5: Short | E5: Done
A6: 3 | B6: Staff training on segregation | C6: Train housekeeping on segregation protocols; quarterly refresher sessions | D6: Short | E6: IP
A7: 4 | B7: Awareness campaigns — 3R | C7: Poster campaigns, eco-club drives on Reduce-Reuse-Recycle; annual Zero Waste Day | D7: Short | E7: IP
A8: 5 | B8: Small-scale composting/vermicomposting | C8: Pilot compost pit for canteen & garden organic waste | D8: Short | E8: Done
A9: 6 | B9: Full-scale vermicompost unit | C9: Establish permanent composting unit; process all campus biodegradable waste | D9: Mid | E9: Planned
A10: 7 | B10: Recycling & scrap hub | C10: Create storage hubs for paper, plastic, e-waste, metal; partner with recyclers | D10: Mid | E10: Planned
A11: 8 | B11: E-office / digital workflows | C11: Mandate e-submissions, digital approvals, green computing to reduce paper waste | D11: Mid | E11: IP
A12: 9 | B12: Annual waste audits institutionalized | C12: Biannual audits tracking waste reduction %, landfill diversion rate | D12: Mid | E12: Planned
A13: 10 | B13: Municipal / recycler partnerships | C13: Formal MoUs with municipal corporation, authorized recyclers, CBWTF operators | D13: Mid | E13: Planned
A14: 11 | B14: Student innovation challenges | C14: NSS/NCC/eco-club projects on waste reduction; annual waste hackathon | D14: Mid | E14: Planned
A15: 12 | B15: IoT-enabled smart bins | C15: Deploy smart bins with fill-level sensors + digital dashboard for real-time tracking | D15: Long | E15: Planned
... A19: 16 | B19: ISO 14001 / Green Campus certification | C19: Leverage waste management data for ISO & Green Campus recognition | D19: Long | E19: Planned
A21: Progress Summary — Auto-Calculated
A22: Total Initiatives | D22: =16 -> 16
A23: Completed | D23: =COUNTIF(E4:E19,"Done") -> 2
A24: In Progress | D24: =COUNTIF(E4:E19,"IP") -> 4
A25: Planned | D25: =COUNTIF(E4:E19,"Planned") -> 10
A26: Total Budget (₹ Lakhs) | D26: =SUM(F4:F19) -> 0
A27: Completion Rate (%) | D27: =IFERROR(COUNTIF(E4:E19,"Done")/16*100,0) -> 12.5

Sheet 8. Data Quality Audit
A1: WASTE AUDIT — DATA QUALITY & VALIDATION CHECKLIST
A2: Validates waste data for NAAC / NIRF / ISO 14001 / Green Campus / THE Impact submissions
A3: # | B3: Quality Check | C3: Description | D3: Status (✓/✗/IP) | E3: Date | F3: Reviewer
A4: 1 | B4: Waste categories complete | C4: All 14 waste types from institutional classification covered (organic, paper, plastic, e-waste, metal, electrical, glass, timber, sanitary, construction, domestic, biomedical, oil/grease, other)
A5: 2 | B5: Monthly data continuity | C5: 12 months of waste data (Apr 2026 – Mar 2027) with no missing months
A6: 3 | B6: Weighing methodology | C6: Waste weighed using calibrated scales at source; not estimated from bin volume
A7: 4 | B7: Segregation at source verified | C7: Color-coded bins (green/blue/red) deployed at all locations; segregation compliance >80%
A8: 5 | B8: Composting input-output tracked | C8: Total organic input, compost output, and conversion rate documented monthly
A9: 6 | B9: Recycler authorization verified | C9: All recyclers / e-waste handlers / CBWTF operators have valid CPCB / SPCB authorization
A10: 7 | B10: Revenue receipts on file | C10: Sale of paper, metal, scrap backed by buyer receipts / invoices / weighbridge slips
A11: 8 | B11: Diversion rate calculation | C11: Diversion = (Recycled + Composted + Sold) / Total Generated × 100; verified for all categories
A12: 9 | B12: Source-wise inventory reconciled | C12: Sum of source-wise monthly waste = total monthly waste in Sheet 2
A13: 10 | B13: E-waste manifest maintained | C13: E-waste collection, storage, and handover to authorized recycler documented per E-Waste Rules 2022
A14: 11 | B14: Biomedical waste log maintained | C14: BMW collection, color-coded segregation, and CBWTF handover logged per BMW Rules 2016
A15: 12 | B15: Hazardous waste register | C15: Chemicals, oil, grease disposal in lined pits documented; no soil contamination evidence
... A23: 20 | B23: Competent authority sign-off | C23: Final Waste Audit Report signed by Principal / Registrar / Environmental Officer
A25: Audit Completion Summary
A26: Checks Completed (✓) | D26: =COUNTIF(D4:D23,"✓") -> 0
A27: Completion Rate (%) | D27: =IFERROR(COUNTIF(D4:D23,"✓")/20*100,0) -> 0
